ejemplos/__init__.py
ejemplos/main.py
ejemplos/monitor.py
ejemplos/remote_service.py
ejemplos/remote_tunnel.py
ejemplos/service_installer.py
pc_health_check-0.1.1.dist-info/METADATA
pc_health_check-0.1.1.dist-info/WHEEL
pc_health_check-0.1.1.dist-info/entry_points.txt
pc_health_check-0.1.1.dist-info/top_level.txt
pc_health_check-0.1.1.dist-info/RECORD
