Metadata-Version: 2.1
Name: pc-health-check
Version: 0.1.1
Summary: Herramienta de monitorización de recursos de su equipo PC, Gratis.
License: MIT
Keywords: sistema,recursos,gratis,libre,seguro
Requires-Dist: psutil
Requires-Dist: colorama
Requires-Dist: websockets
